{"465": "", "407": "", "523": "", "348": "", "931": "", "724": "", "871": "", "794": "", "700": "F10", "120": "Rewind", "178": "F1", "294": "F3", "236": "F2", "410": "F5", "468": "F6", "352": "F4", "642": "F9", "584": "F8", "177": "Pag\ndown", "234": "", "291": "Sleep", "260": "", "318": "Insert", "608": "", "434": "", "550": "", "492": "", "666": "", "376": "", "504": "", "446": "", "678": "", "562": "", "620": "", "736": "", "388": "", "330": "", "581": "", "755": "", "639": "", "697": "", "813": "", "417": "", "486": "", "555": "", "816": "F12", "758": "F11", "874": "", "898": "", "840": "", "782": "", "956": "", "910": "", "852": "", "968": "", "929": "", "987": "", "1106": "", "1047": "", "989": "", "1105": "", "1163": "", "1221": "", "526": "F7", "1013": "", "1050": "", "1107": "", "1164": "", "317": "", "280": "", "81": "", "44": "", "97": "", "281": "", "244": ""}